{"width":512,"imagePath":"FemaleZ_tex.png","height":512,"name":"FemaleZ","SubTexture":[{"width":121,"y":1,"height":251,"name":"FemaleZ/FemaleZ_ypf","x":256},{"width":127,"y":1,"height":279,"name":"FemaleZ/FemaleZ_zpf","x":127},{"width":124,"y":1,"height":329,"name":"FemaleZ/FemaleZ_wq","x":1},{"width":78,"y":254,"height":192,"name":"FemaleZ/FemaleZ_yt","x":256},{"width":41,"y":282,"height":217,"name":"FemaleZ/FemaleZ_zt","x":127},{"width":62,"y":332,"height":102,"name":"FemaleZ/FemaleZ_yb","x":1},{"width":82,"y":385,"height":78,"name":"FemaleZ/FemaleZ_tf","x":170},{"width":64,"y":254,"height":98,"name":"FemaleZ/FemaleZ_st","x":336},{"width":45,"y":332,"height":79,"name":"FemaleZ/FemaleZ_zb","x":65},{"width":47,"y":354,"height":65,"name":"FemaleZ/FemaleZ_zs","x":336},{"width":25,"y":475,"height":31,"name":"FemaleZ/FemaleZ_t","x":81},{"width":35,"y":413,"height":60,"name":"FemaleZ/FemaleZ_tf2","x":81},{"width":84,"y":282,"height":101,"name":"FemaleZ/FemaleZ_qb","x":170},{"width":78,"y":436,"height":54,"name":"FemaleZ/FemaleZ_cb","x":1}]}