[1,["25FrSl9bZOl4gxPihjIBYW@6c48a"],["_textureSource"],["cc.SpriteFrame"],0,[{"name":"000005","rect":{"x":4,"y":1,"width":178,"height":90},"offset":{"x":0,"y":-0.5},"originalSize":{"width":186,"height":91},"rotated":false,"capInsets":[0,0,0,0],"vertices":{"rawPosition":[-89,-45,0,89,-45,0,-89,45,0,89,45,0],"indexes":[0,1,2,2,1,3],"uv":[4,90,182,90,4,0,182,0],"nuv":[0.021505376344086023,0,0.978494623655914,0,0.021505376344086023,0.989010989010989,0.978494623655914,0.989010989010989],"minPos":{"x":-89,"y":-45,"z":0},"maxPos":{"x":89,"y":45,"z":0}},"packable":true,"pixelsToUnit":100,"pivot":{"x":0.5,"y":0.5},"meshType":0}],[0],0,[0],[0],[0]]
